MANIFEST.in
README.md
setup.py
django_news_page.egg-info/PKG-INFO
django_news_page.egg-info/SOURCES.txt
django_news_page.egg-info/dependency_links.txt
django_news_page.egg-info/requires.txt
django_news_page.egg-info/top_level.txt
news/__init__.py
news/admin.py
news/models.py
news/urls.py
news/views.py
news/migrations/0001_initial.py
news/migrations/__init__.py
news/templates/news/news_list.html
news/templates/news/news_page.html
news/templates/news/news_widget.html
news/templatetags/__init__.py
news/templatetags/news_tags.py