Metadata-Version: 1.1
Name: django-news-page
Version: 0.1.1
Summary: Simple news applications inspired by django-easy-news
Home-page: https://bitbucket.org/propp/django-news
Author: Dmitry Sobolev
Author-email: propp.ds@gmail.com
License: MIT
Platform: UNKNOWN
Classifier: Development Status :: 3 - Alpha
Classifier: Intended Audience :: Developers
Classifier: License :: OSI Approved :: MIT License
Classifier: Programming Language :: Python :: 2
Classifier: Programming Language :: Python :: 2.6
Classifier: Programming Language :: Python :: 2.7
Classifier: Framework :: Django
Classifier: Framework :: Django :: 1.8
Classifier: Framework :: Django :: 1.9
Classifier: Natural Language :: English
Classifier: Programming Language :: Python :: 2
